etabs_sdk/__init__.py
etabs_sdk/_version.py
etabs_sdk/src/enums.py
etabs_sdk/src/etabs.py
etabs_sdk/src/excepciones.py
etabs_sdk-0.0.1.post0.dist-info/LICENSE
etabs_sdk-0.0.1.post0.dist-info/METADATA
etabs_sdk-0.0.1.post0.dist-info/WHEEL
etabs_sdk-0.0.1.post0.dist-info/top_level.txt
etabs_sdk-0.0.1.post0.dist-info/RECORD
