Metadata-Version: 2.1
Name: etabs-sdk
Version: 0.0.1.post0
Summary: SDK para gestionar las comunicaciones con la API de Etabs con Python
Author-email: Matías Glasner Vivanco <mglasner@iec.cl>, José Luis Barrios <jlbarrios@iec.cl>, Jorge Araya Varela <jaraya@iec.cl>
License: Acuerdo de Licencia de Software de Código Abierto para etabs-sdk
Project-URL: source, https://github.com/iec-ingenieria/etabs-sdk
Keywords: python,engineering,structural engineering,seismic,earthquakes,structural design,etabs,ingeniería,ingeniería estructural,sismo,terremotos,sdk
Requires-Python: >=3.11
License-File: LICENSE
Requires-Dist: comtypes ==1.2.1
Requires-Dist: tabulate ==0.9.0
Provides-Extra: dev
Requires-Dist: pytest ==8.1.1 ; extra == 'dev'
Requires-Dist: ruff ==0.3.7 ; extra == 'dev'
Requires-Dist: mypy ==1.9.0 ; extra == 'dev'
